magen_policy_service-1.0a1.data/scripts/policy_server.py
magen_policy_service-1.0a1.data/scripts/policy_server_wrapper.sh
magen_policy_service-1.0a1.dist-info/DESCRIPTION.rst
magen_policy_service-1.0a1.dist-info/METADATA
magen_policy_service-1.0a1.dist-info/RECORD
magen_policy_service-1.0a1.dist-info/WHEEL
magen_policy_service-1.0a1.dist-info/metadata.json
magen_policy_service-1.0a1.dist-info/top_level.txt
policy/__init__.py
policy/grouppolicy.txt
policy/userpolicy.txt
policy/google_maps_apis/__init__.py
policy/google_maps_apis/geocode_apis.py
policy/mongo_apis/__init__.py
policy/mongo_apis/mongo_policy_contract.py
policy/mongo_apis/mongo_policy_contract_api.py
policy/mongo_apis/mongo_policy_instance.py
policy/mongo_apis/mongo_policy_instance_api.py
policy/mongo_apis/mongo_policy_session.py
policy/mongo_apis/mongo_policy_session_api.py
policy/mongo_apis/mongo_policy_template.py
policy/mongo_apis/mongo_policy_template_api.py
policy/policy_apis/__init__.py
policy/policy_apis/policy_contract_api.py
policy/policy_apis/policy_instance_api.py
policy/policy_apis/policy_session_api.py
policy/policy_apis/policy_template_api.py
policy/policy_apis/policy_validation_api.py
policy/policy_libs/__init__.py
policy/policy_libs/plib_idsvc.py
policy/policy_libs/plib_ingestsvc.py
policy/policy_libs/plib_keysvc.py
policy/policy_libs/plib_utils.py
policy/policy_libs/policy_dctx_state.py
policy/policy_libs/policy_eventing.py
policy/policy_libs/policy_state.py
policy/policy_server/__init__.py
policy/policy_server/policy_contract_rest_api.py
policy/policy_server/policy_instance_rest_api.py
policy/policy_server/policy_misc_rest_api.py
policy/policy_server/policy_reset_rest_api.py
policy/policy_server/policy_server.py
policy/policy_server/policy_session_rest_api.py
policy/policy_server/policy_template_rest_api.py
policy/policy_server/policy_validation_rest_api.py
