Metadata-Version: 2.0
Name: magen-policy-service
Version: 1.0a1
Summary: Policy Microservice Package
Home-page: UNKNOWN
Author: Reinaldo Penno
Author-email: repenno@cisco.com
License: UNKNOWN
Platform: UNKNOWN
Classifier: Development Status :: 2 - Pre-Alpha
Classifier: Intended Audience :: Education
Classifier: Intended Audience :: Financial and Insurance Industry
Classifier: Intended Audience :: Healthcare Industry
Classifier: Intended Audience :: Legal Industry
Classifier: Topic :: Security
Classifier: License :: Other/Proprietary License
Classifier: Programming Language :: Python :: 3.5
Requires-Dist: Flask (>=0.12.2)
Requires-Dist: Flask-Cors (>=3.0.3)
Requires-Dist: Sphinx (>=1.6.3)
Requires-Dist: aniso8601 (>=1.2.1)
Requires-Dist: coverage (>=4.4.1)
Requires-Dist: flake8 (>=3.3.0)
Requires-Dist: googlemaps (>=2.5.1)
Requires-Dist: magen-id-client (==1.0a1)
Requires-Dist: magen-location-service (>=1.0a1)
Requires-Dist: magen-logger (==1.0a1)
Requires-Dist: magen-mongo (==1.0a1)
Requires-Dist: magen-rest-service (==1.0a1)
Requires-Dist: magen-statistics-service (==1.0a1)
Requires-Dist: magen-utils (==1.0a1)
Requires-Dist: pymongo (>=3.4.0)
Requires-Dist: pytest (>=3.1.3)
Requires-Dist: requests (>=2.13.0)
Requires-Dist: responses (==0.5.1)
Requires-Dist: wheel (>=0.30.0a0)
